[
  {
    "MODEL_KEY": 878789,
    "DATE_KEY": "2020-07-26",
    "DATE_GRANULARITY": "Daily",
    "GEO_KEY": 12408,
    "GEO_GRANULARITY": "STATE",
    "MODELED_DATE": "2020-10-14",
    "MODEL_VERSION": 61998,
    "location_name": "Baltimore",
    "allbed_mean": 26.060026190476197,
    "allbed_lower": 0,
    "allbed_upper": 104.5125,
    "ICUbed_mean": 11.6911785714286,
    "ICUbed_lower": 0,
    "ICUbed_upper": 50.0375,
    "InvVen_mean": 11.1909785714286,
    "InvVen_lower": 0,
    "InvVen_upper": 47.5375,
    "deaths_mean": 1.8221795460189,
    "deaths_lower": 0,
    "deaths_upper": 7.46746732918989,
    "admis_mean": 3.9913166666666697,
    "admis_lower": 0,
    "admis_upper": 17.025,
    "newICU_mean": 1.95697142857143,
    "newICU_lower": 0,
    "newICU_upper": 8.51249999999999,
    "totdea_mean": 2931.99484289759,
    "totdea_lower": 2746.13194526757,
    "totdea_upper": 3272.75000560221,
    "bedover_mean": 0,
    "bedover_lower": 0,
    "bedover_upper": 0,
    "icuover_mean": 0,
    "icuover_lower": 0,
    "icuover_upper": 0,
    "deaths_mean_smoothed": 1.8221795460189,
    "deaths_lower_smoothed": 0,
    "deaths_upper_smoothed": 7.46746732918989,
    "totdea_mean_smoothed": 2931.99484289759,
    "totdea_lower_smoothed": 2746.13194526757,
    "totdea_upper_smoothed": 3272.75000560221,
    "mobility_data_type": "projected",
    "mobility_composite": -20.273341814248894,
    "total_tests_data_type": "projected",
    "total_tests": 36433.9498879259,
    "confirmed_infections": "NULL",
    "est_infections_mean": 253.551845402777,
    "est_infections_lower": 0,
    "est_infections_upper": 1201.04404444527,
    "REC_INS_TS": "2020-07-26 22:40:31",
    "REC_UPD_TS": "2020-07-26 22:40:31",
    "Path_Update_Val": "2020_17_18"
  },
  {
    "MODEL_KEY": 885315,
    "DATE_KEY": "2020-07-26",
    "DATE_GRANULARITY": "Daily",
    "GEO_KEY": 12410,
    "GEO_GRANULARITY": "STATE",
    "MODELED_DATE": "2020-10-12",
    "MODEL_VERSION": 68524,
    "location_name": "Los Angeles",
    "allbed_mean": 180.328087094278,
    "allbed_lower": 0,
    "allbed_upper": 890.222222222222,
    "ICUbed_mean": 80.4776691764118,
    "ICUbed_lower": 0,
    "ICUbed_upper": 396.791666666667,
    "InvVen_mean": 77.1829942255457,
    "InvVen_lower": 0,
    "InvVen_upper": 382.333333333333,
    "deaths_mean": 12.5623787426142,
    "deaths_lower": 0,
    "deaths_upper": 58.5107042391852,
    "admis_mean": 29.489872968534694,
    "admis_lower": 0,
    "admis_upper": 161.517857142857,
    "newICU_mean": 13.8625132661456,
    "newICU_lower": 0,
    "newICU_upper": 71.11904761904759,
    "totdea_mean": 6581.6710118803785,
    "totdea_lower": 5711.60868696656,
    "totdea_upper": 8168.055238212809,
    "bedover_mean": 0,
    "bedover_lower": 0,
    "bedover_upper": 0,
    "icuover_mean": 0,
    "icuover_lower": 0,
    "icuover_upper": 0,
    "deaths_mean_smoothed": 12.5623787426142,
    "deaths_lower_smoothed": 0,
    "deaths_upper_smoothed": 58.5107042391852,
    "totdea_mean_smoothed": 6581.6710118803785,
    "totdea_lower_smoothed": 5711.60868696656,
    "totdea_upper_smoothed": 8168.055238212809,
    "mobility_data_type": "projected",
    "mobility_composite": -11.2293585689206,
    "total_tests_data_type": "projected",
    "total_tests": 12628.9571178898,
    "confirmed_infections": "NULL",
    "est_infections_mean": 2051.41294199023,
    "est_infections_lower": 0,
    "est_infections_upper": 10570.239405234499,
    "REC_INS_TS": "2020-07-26 22:40:31",
    "REC_UPD_TS": "2020-07-26 22:40:31",
    "Path_Update_Val": "2020_17_18"
  },
  {
    "MODEL_KEY": 877016,
    "DATE_KEY": "2020-07-26",
    "DATE_GRANULARITY": "Daily",
    "GEO_KEY": 12407,
    "GEO_GRANULARITY": "STATE",
    "MODELED_DATE": "2020-05-26",
    "MODEL_VERSION": 60225,
    "location_name": "Fort Worth Scotia",
    "allbed_mean": 0.23765,
    "allbed_lower": 0.05,
    "allbed_upper": 0.5,
    "ICUbed_mean": 0.1319,
    "ICUbed_lower": 0,
    "ICUbed_upper": 0.35,
    "InvVen_mean": 0.01835,
    "InvVen_lower": 0,
    "InvVen_upper": 0.1,
    "deaths_mean": 1,
    "deaths_lower": 1,
    "deaths_upper": 1,
    "admis_mean": 0,
    "admis_lower": 0,
    "admis_upper": 0,
    "newICU_mean": 0,
    "newICU_lower": 0,
    "newICU_upper": 0,
    "totdea_mean": 59,
    "totdea_lower": 59,
    "totdea_upper": 59,
    "bedover_mean": 0,
    "bedover_lower": 0,
    "bedover_upper": 0,
    "icuover_mean": 0,
    "icuover_lower": 0,
    "icuover_upper": 0,
    "deaths_mean_smoothed": 0.31282264060909903,
    "deaths_lower_smoothed": 0.31282264060909903,
    "deaths_upper_smoothed": 0.31282264060909903,
    "totdea_mean_smoothed": 58.56600574031921,
    "totdea_lower_smoothed": 58.56600574031921,
    "totdea_upper_smoothed": 58.56600574031921,
    "mobility_data_type": "observed",
    "mobility_composite": -38.2466536414071,
    "total_tests_data_type": "observed",
    "total_tests": 480.25245717269013,
    "confirmed_infections": 0.9999999999990908,
    "est_infections_mean": 9.76746993547,
    "est_infections_lower": 6.72188342144047,
    "est_infections_upper": 13.682638985587001,
    "REC_INS_TS": "2020-07-26 22:40:31",
    "REC_UPD_TS": "2020-07-26 22:40:31",
    "Path_Update_Val": "2020_17_18"
  },
  {
    "MODEL_KEY": 891004,
    "DATE_KEY": "2020-07-26",
    "DATE_GRANULARITY": "Daily",
    "GEO_KEY": 12411,
    "GEO_GRANULARITY": "STATE",
    "MODELED_DATE": "2020-09-19",
    "MODEL_VERSION": 74213,
    "location_name": "Bowie",
    "allbed_mean": 0,
    "allbed_lower": 0,
    "allbed_upper": 0,
    "ICUbed_mean": 0,
    "ICUbed_lower": 0,
    "ICUbed_upper": 0,
    "InvVen_mean": 0,
    "InvVen_lower": 0,
    "InvVen_upper": 0,
    "deaths_mean": 0.000705726712951989,
    "deaths_lower": 0,
    "deaths_upper": 0.0018436005473056105,
    "admis_mean": 0,
    "admis_lower": 0,
    "admis_upper": 0,
    "newICU_mean": 0,
    "newICU_lower": 0,
    "newICU_upper": 0,
    "totdea_mean": 17.716261063430604,
    "totdea_lower": 15.8485163505211,
    "totdea_upper": 20.199814526129803,
    "bedover_mean": 0,
    "bedover_lower": 0,
    "bedover_upper": 0,
    "icuover_mean": 0,
    "icuover_lower": 0,
    "icuover_upper": 0,
    "deaths_mean_smoothed": 0.000705726712951989,
    "deaths_lower_smoothed": 0,
    "deaths_upper_smoothed": 0.0018436005473056105,
    "totdea_mean_smoothed": 17.716261063430604,
    "totdea_lower_smoothed": 15.8485163505211,
    "totdea_upper_smoothed": 20.199814526129803,
    "mobility_data_type": "projected",
    "mobility_composite": -11.4066027144274,
    "total_tests_data_type": "projected",
    "total_tests": 1097.98247551544,
    "confirmed_infections": "NULL",
    "est_infections_mean": 0.0148439741460609,
    "est_infections_lower": 0,
    "est_infections_upper": 0.0403456414176617,
    "REC_INS_TS": "2020-07-26 22:40:31",
    "REC_UPD_TS": "2020-07-26 22:40:31",
    "Path_Update_Val": "2020_17_18"
  },
  {
    "MODEL_KEY": 732743,
    "DATE_KEY": "2020-07-11",
    "DATE_GRANULARITY": "Daily",
    "GEO_KEY": 28,
    "GEO_GRANULARITY": "COUNTRY",
    "MODELED_DATE": "2020-11-01",
    "MODEL_VERSION": 4352,
    "location_name": "Antigua and Barbuda",
    "allbed_mean": 0,
    "allbed_lower": 0,
    "allbed_upper": 0,
    "ICUbed_mean": 0,
    "ICUbed_lower": 0,
    "ICUbed_upper": 0,
    "InvVen_mean": 0,
    "InvVen_lower": 0,
    "InvVen_upper": 0,
    "deaths_mean": 2.75634847755057e-7,
    "deaths_lower": 1.3531735965077695e-7,
    "deaths_upper": 4.8440726625465e-7,
    "admis_mean": 0,
    "admis_lower": 0,
    "admis_upper": 0,
    "newICU_mean": 0,
    "newICU_lower": 0,
    "newICU_upper": 0,
    "totdea_mean": 3.47320122308194,
    "totdea_lower": 3.4543813874529903,
    "totdea_upper": 3.49052129203098,
    "bedover_mean": 0,
    "bedover_lower": 0,
    "bedover_upper": 0,
    "icuover_mean": 0,
    "icuover_lower": 0,
    "icuover_upper": 0,
    "deaths_mean_smoothed": 2.75634847755057e-7,
    "deaths_lower_smoothed": 1.3531735965077695e-7,
    "deaths_upper_smoothed": 4.8440726625465e-7,
    "totdea_mean_smoothed": 3.47320122308194,
    "totdea_lower_smoothed": 3.4543813874529903,
    "totdea_upper_smoothed": 3.49052129203098,
    "mobility_data_type": "projected",
    "mobility_composite": -4.22419749135809,
    "total_tests_data_type": "projected",
    "total_tests": 66.5777611218941,
    "confirmed_infections": "NULL",
    "est_infections_mean": 0.0000105621759867063,
    "est_infections_lower": 0.00000416735238104593,
    "est_infections_upper": 0.0000201386668777559,
    "REC_INS_TS": "2020-07-15 16:57:32",
    "REC_UPD_TS": "2020-07-15 16:57:32",
    "Path_Update_Val": "2020/07/11"
  },
  {
    "MODEL_KEY": 890882,
    "DATE_KEY": "2020-07-26",
    "DATE_GRANULARITY": "Daily",
    "GEO_KEY": 12411,
    "GEO_GRANULARITY": "STATE",
    "MODELED_DATE": "2020-05-20",
    "MODEL_VERSION": 74091,
    "location_name": "Saskatchewan",
    "allbed_mean": 0,
    "allbed_lower": 0,
    "allbed_upper": 0,
    "ICUbed_mean": 0,
    "ICUbed_lower": 0,
    "ICUbed_upper": 0,
    "InvVen_mean": 0,
    "InvVen_lower": 0,
    "InvVen_upper": 0,
    "deaths_mean": 0,
    "deaths_lower": 0,
    "deaths_upper": 0,
    "admis_mean": 0,
    "admis_lower": 0,
    "admis_upper": 0,
    "newICU_mean": 0,
    "newICU_lower": 0,
    "newICU_upper": 0,
    "totdea_mean": 6,
    "totdea_lower": 6,
    "totdea_upper": 6,
    "bedover_mean": 0,
    "bedover_lower": 0,
    "bedover_upper": 0,
    "icuover_mean": 0,
    "icuover_lower": 0,
    "icuover_upper": 0,
    "deaths_mean_smoothed": 0.19010650605186,
    "deaths_lower_smoothed": 0.19010650605186,
    "deaths_upper_smoothed": 0.19010650605186,
    "totdea_mean_smoothed": 7.07364734538419,
    "totdea_lower_smoothed": 7.07364734538419,
    "totdea_upper_smoothed": 7.07364734538419,
    "mobility_data_type": "observed",
    "mobility_composite": -33.7959180377897,
    "total_tests_data_type": "observed",
    "total_tests": 433.423694176024,
    "confirmed_infections": 20.999999999999694,
    "est_infections_mean": 16.872499049219,
    "est_infections_lower": 7.0293513768819205,
    "est_infections_upper": 35.6484306264797,
    "REC_INS_TS": "2020-07-26 22:40:31",
    "REC_UPD_TS": "2020-07-26 22:40:31",
    "Path_Update_Val": "2020_17_18"
  },
  {
    "MODEL_KEY": 869226,
    "DATE_KEY": "2020-07-26",
    "DATE_GRANULARITY": "Daily",
    "GEO_KEY": 492,
    "GEO_GRANULARITY": "COUNTRY",
    "MODELED_DATE": "2020-09-01",
    "MODEL_VERSION": 52435,
    "location_name": "Monaco",
    "allbed_mean": 0,
    "allbed_lower": 0,
    "allbed_upper": 0,
    "ICUbed_mean": 0,
    "ICUbed_lower": 0,
    "ICUbed_upper": 0,
    "InvVen_mean": 0,
    "InvVen_lower": 0,
    "InvVen_upper": 0,
    "deaths_mean": 0.009214164097228791,
    "deaths_lower": 0,
    "deaths_upper": 0.014477078251208,
    "admis_mean": 0,
    "admis_lower": 0,
    "admis_upper": 0,
    "newICU_mean": 0,
    "newICU_lower": 0,
    "newICU_upper": 0,
    "totdea_mean": 4.7208594579734005,
    "totdea_lower": 4.40327583001055,
    "totdea_upper": 4.87135290246435,
    "bedover_mean": 0,
    "bedover_lower": 0,
    "bedover_upper": 0,
    "icuover_mean": 0,
    "icuover_lower": 0,
    "icuover_upper": 0,
    "deaths_mean_smoothed": 0.009214164097228791,
    "deaths_lower_smoothed": 0,
    "deaths_upper_smoothed": 0.014477078251208,
    "totdea_mean_smoothed": 4.7208594579734005,
    "totdea_lower_smoothed": 4.40327583001055,
    "totdea_upper_smoothed": 4.87135290246435,
    "mobility_data_type": "projected",
    "mobility_composite": -13.447669131208999,
    "total_tests_data_type": "projected",
    "total_tests": 72.62815202484259,
    "confirmed_infections": "NULL",
    "est_infections_mean": 0.82050092486864,
    "est_infections_lower": 0,
    "est_infections_upper": 1.42437554612879,
    "REC_INS_TS": "2020-07-26 22:40:31",
    "REC_UPD_TS": "2020-07-26 22:40:31",
    "Path_Update_Val": "2020_17_18"
  },
  {
    "MODEL_KEY": 869165,
    "DATE_KEY": "2020-07-26",
    "DATE_GRANULARITY": "Daily",
    "GEO_KEY": 492,
    "GEO_GRANULARITY": "COUNTRY",
    "MODELED_DATE": "2020-07-02",
    "MODEL_VERSION": 52374,
    "location_name": "Monaco",
    "allbed_mean": 0,
    "allbed_lower": 0,
    "allbed_upper": 0,
    "ICUbed_mean": 0,
    "ICUbed_lower": 0,
    "ICUbed_upper": 0,
    "InvVen_mean": 0,
    "InvVen_lower": 0,
    "InvVen_upper": 0,
    "deaths_mean": 0,
    "deaths_lower": 0,
    "deaths_upper": 0,
    "admis_mean": 0,
    "admis_lower": 0,
    "admis_upper": 0,
    "newICU_mean": 0,
    "newICU_lower": 0,
    "newICU_upper": 0,
    "totdea_mean": 4,
    "totdea_lower": 4,
    "totdea_upper": 4,
    "bedover_mean": 0,
    "bedover_lower": 0,
    "bedover_upper": 0,
    "icuover_mean": 0,
    "icuover_lower": 0,
    "icuover_upper": 0,
    "deaths_mean_smoothed": 0.004948217636319361,
    "deaths_lower_smoothed": 0.004948217636319361,
    "deaths_upper_smoothed": 0.004948217636319361,
    "totdea_mean_smoothed": 4.31085015142096,
    "totdea_lower_smoothed": 4.31085015142096,
    "totdea_upper_smoothed": 4.31085015142096,
    "mobility_data_type": "observed",
    "mobility_composite": -19.0311599862197,
    "total_tests_data_type": "projected",
    "total_tests": 48.8092419521791,
    "confirmed_infections": 2.99999999999996,
    "est_infections_mean": 0.387071929595367,
    "est_infections_lower": 0.257427190446651,
    "est_infections_upper": 0.541400860987596,
    "REC_INS_TS": "2020-07-26 22:40:31",
    "REC_UPD_TS": "2020-07-26 22:40:31",
    "Path_Update_Val": "2020_17_18"
  },
  {
    "MODEL_KEY": 869083,
    "DATE_KEY": "2020-07-26",
    "DATE_GRANULARITY": "Daily",
    "GEO_KEY": 492,
    "GEO_GRANULARITY": "COUNTRY",
    "MODELED_DATE": "2020-04-11",
    "MODEL_VERSION": 52292,
    "location_name": "Monaco",
    "allbed_mean": 0,
    "allbed_lower": 0,
    "allbed_upper": 0,
    "ICUbed_mean": 0,
    "ICUbed_lower": 0,
    "ICUbed_upper": 0,
    "InvVen_mean": 0,
    "InvVen_lower": 0,
    "InvVen_upper": 0,
    "deaths_mean": 0,
    "deaths_lower": 0,
    "deaths_upper": 0,
    "admis_mean": 0,
    "admis_lower": 0,
    "admis_upper": 0,
    "newICU_mean": 0,
    "newICU_lower": 0,
    "newICU_upper": 0,
    "totdea_mean": 1,
    "totdea_lower": 1,
    "totdea_upper": 1,
    "bedover_mean": 0,
    "bedover_lower": 0,
    "bedover_upper": 0,
    "icuover_mean": 0,
    "icuover_lower": 0,
    "icuover_upper": 0,
    "deaths_mean_smoothed": 0.14171507083972,
    "deaths_lower_smoothed": 0.14171507083972,
    "deaths_upper_smoothed": 0.14171507083972,
    "totdea_mean_smoothed": 1.70205422382301,
    "totdea_lower_smoothed": 1.70205422382301,
    "totdea_upper_smoothed": 1.70205422382301,
    "mobility_data_type": "observed",
    "mobility_composite": -63.6865509373936,
    "total_tests_data_type": "projected",
    "total_tests": 16.7903792315496,
    "confirmed_infections": 2.00000000000003,
    "est_infections_mean": 3.72375488443556,
    "est_infections_lower": 2.13399697326367,
    "est_infections_upper": 5.832046623563159,
    "REC_INS_TS": "2020-07-26 22:40:31",
    "REC_UPD_TS": "2020-07-26 22:40:31",
    "Path_Update_Val": "2020_17_18"
  },
  {
    "MODEL_KEY": 885193,
    "DATE_KEY": "2020-07-26",
    "DATE_GRANULARITY": "Daily",
    "GEO_KEY": 12410,
    "GEO_GRANULARITY": "STATE",
    "MODELED_DATE": "2020-06-12",
    "MODEL_VERSION": 68402,
    "location_name": "Quebec",
    "allbed_mean": 447.5307785875541,
    "allbed_lower": 379.43055555555605,
    "allbed_upper": 528.345588235294,
    "ICUbed_mean": 195.600632295895,
    "ICUbed_lower": 189.284340659341,
    "ICUbed_upper": 201.671875,
    "InvVen_mean": 182.14571336687,
    "InvVen_lower": 180,
    "InvVen_upper": 184.73684210526298,
    "deaths_mean": 43,
    "deaths_lower": 43,
    "deaths_upper": 43,
    "admis_mean": 42.3506621407059,
    "admis_lower": 25.714285714285694,
    "admis_upper": 65.0277777777778,
    "newICU_mean": 20.7965498411547,
    "newICU_lower": 20,
    "newICU_upper": 22.7777777777778,
    "totdea_mean": 5148,
    "totdea_lower": 5148,
    "totdea_upper": 5148,
    "bedover_mean": 0,
    "bedover_lower": 0,
    "bedover_upper": 0,
    "icuover_mean": 0,
    "icuover_lower": 0,
    "icuover_upper": 0,
    "deaths_mean_smoothed": 35.4020952778701,
    "deaths_lower_smoothed": 35.4020952778701,
    "deaths_upper_smoothed": 35.4020952778701,
    "totdea_mean_smoothed": 5162.27266341863,
    "totdea_lower_smoothed": 5162.27266341863,
    "totdea_upper_smoothed": 5162.27266341863,
    "mobility_data_type": "observed",
    "mobility_composite": -28.7222596422864,
    "total_tests_data_type": "observed",
    "total_tests": 5356.43805301516,
    "confirmed_infections": 181.00000000000702,
    "est_infections_mean": 1159.48265765109,
    "est_infections_lower": 980.998690735313,
    "est_infections_upper": 1367.93278365104,
    "REC_INS_TS": "2020-07-26 22:40:31",
    "REC_UPD_TS": "2020-07-26 22:40:31",
    "Path_Update_Val": "2020_17_18"
  },
  {
    "MODEL_KEY": 732579,
    "DATE_KEY": "2020-07-11",
    "DATE_GRANULARITY": "Daily",
    "GEO_KEY": 28,
    "GEO_GRANULARITY": "COUNTRY",
    "MODELED_DATE": "2020-05-21",
    "MODEL_VERSION": 4188,
    "location_name": "Antigua and Barbuda",
    "allbed_mean": 0,
    "allbed_lower": 0,
    "allbed_upper": 0,
    "ICUbed_mean": 0,
    "ICUbed_lower": 0,
    "ICUbed_upper": 0,
    "InvVen_mean": 0,
    "InvVen_lower": 0,
    "InvVen_upper": 0,
    "deaths_mean": 0,
    "deaths_lower": 0,
    "deaths_upper": 0,
    "admis_mean": 0,
    "admis_lower": 0,
    "admis_upper": 0,
    "newICU_mean": 0,
    "newICU_lower": 0,
    "newICU_upper": 0,
    "totdea_mean": 3,
    "totdea_lower": 3,
    "totdea_upper": 3,
    "bedover_mean": 0,
    "bedover_lower": 0,
    "bedover_upper": 0,
    "icuover_mean": 0,
    "icuover_lower": 0,
    "icuover_upper": 0,
    "deaths_mean_smoothed": 0.00429826934834976,
    "deaths_lower_smoothed": 0.00429826934834976,
    "deaths_upper_smoothed": 0.00429826934834976,
    "totdea_mean_smoothed": 3.1431792908791203,
    "totdea_lower_smoothed": 3.1431792908791203,
    "totdea_upper_smoothed": 3.1431792908791203,
    "mobility_data_type": "observed",
    "mobility_composite": -43.33243,
    "total_tests_data_type": "projected",
    "total_tests": 19.9164242672333,
    "confirmed_infections": 0,
    "est_infections_mean": 0.986441681705265,
    "est_infections_lower": 0.965581797683626,
    "est_infections_upper": 1.00753922390618,
    "REC_INS_TS": "2020-07-15 16:57:32",
    "REC_UPD_TS": "2020-07-15 16:57:32",
    "Path_Update_Val": "2020/07/11"
  },
  {
    "MODEL_KEY": 884051,
    "DATE_KEY": "2020-07-26",
    "DATE_GRANULARITY": "Daily",
    "GEO_KEY": 630,
    "GEO_GRANULARITY": "STATE",
    "MODELED_DATE": "2020-04-19",
    "MODEL_VERSION": 67260,
    "location_name": "Puerto Rico",
    "allbed_mean": 39.6594590983578,
    "allbed_lower": 30.5,
    "allbed_upper": 49.65875,
    "ICUbed_mean": 18.897077069748303,
    "ICUbed_lower": 18,
    "ICUbed_upper": 19.5,
    "InvVen_mean": 18.120884321311603,
    "InvVen_lower": 18,
    "InvVen_upper": 18.5,
    "deaths_mean": 2,
    "deaths_lower": 2,
    "deaths_upper": 2,
    "admis_mean": 6.055123185161071,
    "admis_lower": 3.5,
    "admis_upper": 11.0125,
    "newICU_mean": 3.0742561608197403,
    "newICU_lower": 3,
    "newICU_upper": 3.38461538461538,
    "totdea_mean": 62,
    "totdea_lower": 62,
    "totdea_upper": 62,
    "bedover_mean": 0,
    "bedover_lower": 0,
    "bedover_upper": 0,
    "icuover_mean": 0,
    "icuover_lower": 0,
    "icuover_upper": 0,
    "deaths_mean_smoothed": 2.96250231710039,
    "deaths_lower_smoothed": 2.96250231710039,
    "deaths_upper_smoothed": 2.96250231710039,
    "totdea_mean_smoothed": 62.0084421945818,
    "totdea_lower_smoothed": 62.0084421945818,
    "totdea_upper_smoothed": 62.0084421945818,
    "mobility_data_type": "observed",
    "mobility_composite": -55.0753381310119,
    "total_tests_data_type": "observed",
    "total_tests": 485.11837831404006,
    "confirmed_infections": 95.00000000000021,
    "est_infections_mean": 173.786905603326,
    "est_infections_lower": 122.465901370419,
    "est_infections_upper": 237.100073891915,
    "REC_INS_TS": "2020-07-26 22:40:31",
    "REC_UPD_TS": "2020-07-26 22:40:31",
    "Path_Update_Val": "2020_17_18"
  },
  {
    "MODEL_KEY": 829462,
    "DATE_KEY": "2020-07-26",
    "DATE_GRANULARITY": "Daily",
    "GEO_KEY": 12402,
    "GEO_GRANULARITY": "STATE",
    "MODELED_DATE": "2020-07-11",
    "MODEL_VERSION": 13215,
    "location_name": "British Columbia",
    "allbed_mean": 14.1518717193153,
    "allbed_lower": 8.5,
    "allbed_upper": 19.65875,
    "ICUbed_mean": 6.3432954517232,
    "ICUbed_lower": 6,
    "ICUbed_upper": 7,
    "InvVen_mean": 6.04386254696885,
    "InvVen_lower": 6,
    "InvVen_upper": 6.2,
    "deaths_mean": 0,
    "deaths_lower": 0,
    "deaths_upper": 0,
    "admis_mean": 2.08034497664788,
    "admis_lower": 1,
    "admis_upper": 4.05125,
    "newICU_mean": 1.02978828197946,
    "newICU_lower": 1,
    "newICU_upper": 1.15,
    "totdea_mean": 187,
    "totdea_lower": 187,
    "totdea_upper": 187,
    "bedover_mean": 0,
    "bedover_lower": 0,
    "bedover_upper": 0,
    "icuover_mean": 0,
    "icuover_lower": 0,
    "icuover_upper": 0,
    "deaths_mean_smoothed": 1.17827140577401,
    "deaths_lower_smoothed": 1.17827140577401,
    "deaths_upper_smoothed": 1.17827140577401,
    "totdea_mean_smoothed": 183.804563190737,
    "totdea_lower_smoothed": 183.804563190737,
    "totdea_upper_smoothed": 183.804563190737,
    "mobility_data_type": "observed",
    "mobility_composite": -25.9994859072856,
    "total_tests_data_type": "observed",
    "total_tests": 1772.14146404222,
    "confirmed_infections": 0,
    "est_infections_mean": 85.7250080682123,
    "est_infections_lower": 0,
    "est_infections_upper": 177.35168513711497,
    "REC_INS_TS": "2020-07-26 22:40:31",
    "REC_UPD_TS": "2020-07-26 22:40:31",
    "Path_Update_Val": "2020_17_18"
  },
  {
    "MODEL_KEY": 885069,
    "DATE_KEY": "2020-07-26",
    "DATE_GRANULARITY": "Daily",
    "GEO_KEY": 12410,
    "GEO_GRANULARITY": "STATE",
    "MODELED_DATE": "2020-02-09",
    "MODEL_VERSION": 68278,
    "location_name": "Quebec",
    "allbed_mean": 0,
    "allbed_lower": 0,
    "allbed_upper": 0,
    "ICUbed_mean": 0,
    "ICUbed_lower": 0,
    "ICUbed_upper": 0,
    "InvVen_mean": 0,
    "InvVen_lower": 0,
    "InvVen_upper": 0,
    "deaths_mean": 0,
    "deaths_lower": 0,
    "deaths_upper": 0,
    "admis_mean": 0,
    "admis_lower": 0,
    "admis_upper": 0,
    "newICU_mean": 0,
    "newICU_lower": 0,
    "newICU_upper": 0,
    "totdea_mean": 0,
    "totdea_lower": 0,
    "totdea_upper": 0,
    "bedover_mean": 0,
    "bedover_lower": 0,
    "bedover_upper": 0,
    "icuover_mean": 0,
    "icuover_lower": 0,
    "icuover_upper": 0,
    "deaths_mean_smoothed": 0,
    "deaths_lower_smoothed": 0,
    "deaths_upper_smoothed": 0,
    "totdea_mean_smoothed": 0,
    "totdea_lower_smoothed": 0,
    "totdea_upper_smoothed": 0,
    "mobility_data_type": "observed",
    "mobility_composite": 3.55249473899798,
    "total_tests_data_type": "NULL",
    "total_tests": "NULL",
    "confirmed_infections": "NULL",
    "est_infections_mean": 0,
    "est_infections_lower": 0,
    "est_infections_upper": 0,
    "REC_INS_TS": "2020-07-26 22:40:31",
    "REC_UPD_TS": "2020-07-26 22:40:31",
    "Path_Update_Val": "2020_17_18"
  },
  {
    "MODEL_KEY": 732722,
    "DATE_KEY": "2020-07-11",
    "DATE_GRANULARITY": "Daily",
    "GEO_KEY": 28,
    "GEO_GRANULARITY": "COUNTRY",
    "MODELED_DATE": "2020-10-11",
    "MODEL_VERSION": 4331,
    "location_name": "Antigua and Barbuda",
    "allbed_mean": 0,
    "allbed_lower": 0,
    "allbed_upper": 0,
    "ICUbed_mean": 0,
    "ICUbed_lower": 0,
    "ICUbed_upper": 0,
    "InvVen_mean": 0,
    "InvVen_lower": 0,
    "InvVen_upper": 0,
    "deaths_mean": 0.00000178518504882907,
    "deaths_lower": 9.509737258439621e-7,
    "deaths_upper": 0.0000029378195209539507,
    "admis_mean": 0,
    "admis_lower": 0,
    "admis_upper": 0,
    "newICU_mean": 0,
    "newICU_lower": 0,
    "newICU_upper": 0,
    "totdea_mean": 3.47318501056376,
    "totdea_lower": 3.45436674865184,
    "totdea_upper": 3.49049230261492,
    "bedover_mean": 0,
    "bedover_lower": 0,
    "bedover_upper": 0,
    "icuover_mean": 0,
    "icuover_lower": 0,
    "icuover_upper": 0,
    "deaths_mean_smoothed": 0.00000178518504882907,
    "deaths_lower_smoothed": 9.509737258439621e-7,
    "deaths_upper_smoothed": 0.0000029378195209539507,
    "totdea_mean_smoothed": 3.47318501056376,
    "totdea_lower_smoothed": 3.45436674865184,
    "totdea_upper_smoothed": 3.49049230261492,
    "mobility_data_type": "projected",
    "mobility_composite": -7.46263659950864,
    "total_tests_data_type": "projected",
    "total_tests": 60.6028338417241,
    "confirmed_infections": "NULL",
    "est_infections_mean": 0.0000681971492740558,
    "est_infections_lower": 0.0000301603657135274,
    "est_infections_upper": 0.000122699572602869,
    "REC_INS_TS": "2020-07-15 16:57:32",
    "REC_UPD_TS": "2020-07-15 16:57:32",
    "Path_Update_Val": "2020/07/11"
  },
  {
    "MODEL_KEY": 876955,
    "DATE_KEY": "2020-07-26",
    "DATE_GRANULARITY": "Daily",
    "GEO_KEY": 12407,
    "GEO_GRANULARITY": "STATE",
    "MODELED_DATE": "2020-03-26",
    "MODEL_VERSION": 60164,
    "location_name": "Nova Scotia",
    "allbed_mean": 0,
    "allbed_lower": 0,
    "allbed_upper": 0,
    "ICUbed_mean": 0,
    "ICUbed_lower": 0,
    "ICUbed_upper": 0,
    "InvVen_mean": 0,
    "InvVen_lower": 0,
    "InvVen_upper": 0,
    "deaths_mean": 0,
    "deaths_lower": 0,
    "deaths_upper": 0,
    "admis_mean": 0,
    "admis_lower": 0,
    "admis_upper": 0,
    "newICU_mean": 0,
    "newICU_lower": 0,
    "newICU_upper": 0,
    "totdea_mean": 0,
    "totdea_lower": 0,
    "totdea_upper": 0,
    "bedover_mean": 0,
    "bedover_lower": 0,
    "bedover_upper": 0,
    "icuover_mean": 0,
    "icuover_lower": 0,
    "icuover_upper": 0,
    "deaths_mean_smoothed": 0.0161944869044468,
    "deaths_lower_smoothed": 0.0161944869044468,
    "deaths_upper_smoothed": 0.0161944869044468,
    "totdea_mean_smoothed": 0.104133392142318,
    "totdea_lower_smoothed": 0.104133392142318,
    "totdea_upper_smoothed": 0.104133392142318,
    "mobility_data_type": "observed",
    "mobility_composite": -56.36718595336989,
    "total_tests_data_type": "observed",
    "total_tests": 424.259777441676,
    "confirmed_infections": 5.00000000000004,
    "est_infections_mean": 51.5782915626745,
    "est_infections_lower": 27.1563157487632,
    "est_infections_upper": 84.8938174270697,
    "REC_INS_TS": "2020-07-26 22:40:31",
    "REC_UPD_TS": "2020-07-26 22:40:31",
    "Path_Update_Val": "2020_17_18"
  }
]